{
  "id": "ruipeng-zhang",
  "name_en": "Ruipeng Zhang",
  "name_cn": "张瑞鹏",
  "photo": "images/members/ruipeng-zhang.jpg",
  "title_en": "PI, AI4Rad Lab · Assistant Researcher · Shanghai Sixth People's Hospital",
  "title_cn": "AI4Rad Lab 课题组 PI · 助理研究员 · 上海交通大学医学院附属第六人民医院",
  "bio_en": "PI of AI4Rad Lab and Assistant Researcher at Shanghai Sixth People's Hospital, SJTU School of Medicine. PhD in Information and Communication Engineering from Shanghai Jiao Tong University (2024), advised by Prof. Ya Zhang. Research interests include medical vision-language models and cross-distribution generalization on clinical data.",
  "bio_cn": "AI4Rad 实验室课题组 PI、上海交通大学医学院附属第六人民医院放射介入科助理研究员。2024 年于上海交通大学获信息与通信工程博士学位，师从张娅教授。研究方向为医学视觉语言模型与临床数据跨分布泛化。",
  "links": {
    "email": "zhangrp@sjtu.edu.cn",
    "scholar": "https://scholar.google.com/citations?user=m7RzJxwAAAAJ&hl=en",
    "github": "https://github.com/FrankZhangRp/",
    "homepage": "https://frankzhangrp.github.io/"
  },
  "interests_en": [
    "Medical vision-language models",
    "Cross-distribution generalization on clinical data"
  ],
  "interests_cn": [
    "医学视觉语言模型",
    "临床数据跨分布泛化"
  ],
  "news_en": [
    {
      "date": "Jun 2026",
      "highlight": true,
      "text": "LumbarSR — paired clinical CT &amp; micro-CT dataset for lumbar vertebra super-resolution — accepted by <strong><em>Scientific Data</em></strong>. Co-first author."
    },
    {
      "date": "Jan 2026",
      "highlight": true,
      "text": "Paper accepted in <strong><em>npj Digital Medicine</em></strong> (SCI Q1, IF 15.2). Co-first author."
    },
    {
      "date": "Dec 2024",
      "text": "Paper accepted in <strong>FITEE</strong>."
    },
    {
      "date": "Mar 2024",
      "text": "Paper accepted in <strong><em>IEEE Trans. Medical Imaging</em></strong>."
    },
    {
      "date": "Jan 2024",
      "text": "Paper accepted at <strong>ICLR 2024</strong>."
    },
    {
      "date": "Oct 2023",
      "text": "Paper accepted in <strong><em>Transactions on Machine Learning Research</em> (TMLR)</strong>."
    },
    {
      "date": "Sep 2023",
      "text": "Paper accepted at <strong>NeurIPS 2023</strong>."
    },
    {
      "date": "Jun 2023",
      "text": "Paper accepted at <strong>MICCAI 2023</strong>."
    }
  ],
  "news_cn": [
    {
      "date": "2026年6月",
      "highlight": true,
      "text": "LumbarSR —— 配对临床 CT 与显微 CT 的腰椎超分辨率数据集，被 <strong><em>Scientific Data</em></strong> 接收。共同第一作者。"
    },
    {
      "date": "2026年1月",
      "highlight": true,
      "text": "一篇论文被 <strong><em>npj Digital Medicine</em></strong> 接收（SCI Q1, IF 15.2）。共同第一作者。"
    },
    {
      "date": "2024年12月",
      "text": "一篇论文被 <strong>FITEE</strong> 接收。"
    },
    {
      "date": "2024年3月",
      "text": "一篇论文被 <strong><em>IEEE Trans. Medical Imaging</em></strong> 接收。"
    },
    {
      "date": "2024年1月",
      "text": "一篇论文被 <strong>ICLR 2024</strong> 接收。"
    },
    {
      "date": "2023年10月",
      "text": "一篇论文被 <strong><em>Transactions on Machine Learning Research</em> (TMLR)</strong> 接收。"
    },
    {
      "date": "2023年9月",
      "text": "一篇论文被 <strong>NeurIPS 2023</strong> 接收。"
    },
    {
      "date": "2023年6月",
      "text": "一篇论文被 <strong>MICCAI 2023</strong> 接收。"
    }
  ],
  "awards_en": [
    "Outstanding Graduate Student Scholarship, Shanghai Jiao Tong University (2023)",
    "Runner-up, <a href=\"https://breastdensityfl.acr.org/\">Breast Density FL Challenge</a>, <a href=\"https://conferences.miccai.org/2022/en/\">MICCAI 2022</a>",
    "Wu Wen Jun Honorary Doctoral Fellowship, AI Institute, Shanghai Jiao Tong University (2019)",
    "First-class Scholarship, University of Electronic Science and Technology of China (2017)",
    "Second Prize, Mathematical Modeling Competition, UESTC (2017)",
    "First-class Scholarship, UESTC (2016)",
    "Outstanding Individual in Social Practice, UESTC (2016)"
  ],
  "awards_cn": [
    "上海交通大学研究生优秀奖学金（2023 年 12 月）",
    "<a href=\"https://conferences.miccai.org/2022/en/\">MICCAI 2022</a> <a href=\"https://breastdensityfl.acr.org/\">Breast Density FL 挑战赛</a>全球亚军",
    "吴文俊人工智能荣誉博士班入选者（2019 年 9 月）",
    "电子科技大学人民一等奖学金（2017 年 12 月）",
    "电子科技大学数学建模竞赛二等奖（2017 年 6 月）",
    "电子科技大学人民一等奖学金（2016 年 12 月）",
    "电子科技大学社会实践优秀个人（2016 年 10 月）"
  ],
  "services_en": [
    "<strong>Conference Reviewer:</strong> MICCAI 2022, 2023, 2024; ISBI 2024; NeurIPS 2024; ICLR 2025",
    "<strong>Journal Reviewer:</strong> IEEE TCSVT, Pattern Recognition, IEEE JBHI, IEEE TCDS, IEEE TII, IEEE TKDE"
  ],
  "services_cn": [
    "<strong>会议审稿人：</strong>MICCAI 2022、2023、2024；ISBI 2024；NeurIPS 2024；ICLR 2025",
    "<strong>期刊审稿人：</strong>IEEE TCSVT、Pattern Recognition、IEEE JBHI、IEEE TCDS、IEEE TII、IEEE TKDE"
  ]
}